[
  {
    "inputs": [
      {
        "internalType": "address",
        "name": "_nftContract",
        "type": "address"
      },
      {
        "internalType": "address",
        "name": "_nftAdmin",
        "type": "address"
      },
      {
        "internalType": "address",
        "name": "_baseToken",
        "type": "address"
      },
      {
        "internalType": "uint256",
        "name": "_basePrice",
        "type": "uint256"
      },
      {
        "internalType": "address",
        "name": "_randOracle",
        "type": "address"
      }
    ],
    "stateMutability": "nonpayable",
    "type": "constructor"
  },
  {
    "anonymous": false,
    "inputs": [
      {
        "indexed": true,
        "internalType": "address",
        "name": "previousOwner",
        "type": "address"
      },
      {
        "indexed": true,
        "internalType": "address",
        "name": "newOwner",
        "type": "address"
      }
    ],
    "name": "OwnershipTransferred",
    "type": "event"
  },
  {
    "anonymous": false,
    "inputs": [
      {
        "indexed": true,
        "internalType": "address",
        "name": "buyer",
        "type": "address"
      },
      {
        "indexed": false,
        "internalType": "uint256",
        "name": "numberBought",
        "type": "uint256"
      }
    ],
    "name": "TokenTraded",
    "type": "event"
  },
  {
    "anonymous": false,
    "inputs": [
      {
        "indexed": true,
        "internalType": "address",
        "name": "buyer",
        "type": "address"
      },
      {
        "indexed": true,
        "internalType": "address",
        "name": "tokenSrc",
        "type": "address"
      },
      {
        "indexed": false,
        "internalType": "uint256",
        "name": "price",
        "type": "uint256"
      }
    ],
    "name": "TradingPairAdded",
    "type": "event"
  },
  {
    "stateMutability": "payable",
    "type": "fallback"
  },
  {
    "inputs": [
      {
        "internalType": "uint256",
        "name": "_index",
        "type": "uint256"
      },
      {
        "internalType": "uint256",
        "name": "_lower",
        "type": "uint256"
      },
      {
        "internalType": "uint256",
        "name": "_upper",
        "type": "uint256"
      }
    ],
    "name": "addLevelBound",
    "outputs": [],
    "stateMutability": "nonpayable",
    "type": "function"
  },
  {
    "inputs": [
      {
        "internalType": "address",
        "name": "_tokenSrc",
        "type": "address"
      },
      {
        "internalType": "uint256",
        "name": "_discount",
        "type": "uint256"
      }
    ],
    "name": "addTradingPair",
    "outputs": [],
    "stateMutability": "nonpayable",
    "type": "function"
  },
  {
    "inputs": [],
    "name": "basePrice",
    "outputs": [
      {
        "internalType": "uint256",
        "name": "",
        "type": "uint256"
      }
    ],
    "stateMutability": "view",
    "type": "function"
  },
  {
    "inputs": [],
    "name": "baseToken",
    "outputs": [
      {
        "internalType": "address",
        "name": "",
        "type": "address"
      }
    ],
    "stateMutability": "view",
    "type": "function"
  },
  {
    "inputs": [
      {
        "internalType": "address",
        "name": "",
        "type": "address"
      }
    ],
    "name": "discounts",
    "outputs": [
      {
        "internalType": "uint256",
        "name": "",
        "type": "uint256"
      }
    ],
    "stateMutability": "view",
    "type": "function"
  },
  {
    "inputs": [
      {
        "internalType": "address",
        "name": "_tokenSrc",
        "type": "address"
      }
    ],
    "name": "getDiscount",
    "outputs": [
      {
        "internalType": "uint256",
        "name": "",
        "type": "uint256"
      }
    ],
    "stateMutability": "view",
    "type": "function"
  },
  {
    "inputs": [
      {
        "internalType": "address",
        "name": "owner",
        "type": "address"
      }
    ],
    "name": "getLatestBuy",
    "outputs": [
      {
        "internalType": "uint256[]",
        "name": "",
        "type": "uint256[]"
      }
    ],
    "stateMutability": "view",
    "type": "function"
  },
  {
    "inputs": [
      {
        "internalType": "uint256",
        "name": "_index",
        "type": "uint256"
      }
    ],
    "name": "getLevelBound",
    "outputs": [
      {
        "components": [
          {
            "internalType": "uint256",
            "name": "lower",
            "type": "uint256"
          },
          {
            "internalType": "uint256",
            "name": "upper",
            "type": "uint256"
          }
        ],
        "internalType": "struct DggSale.LevelBound",
        "name": "",
        "type": "tuple"
      }
    ],
    "stateMutability": "view",
    "type": "function"
  },
  {
    "inputs": [],
    "name": "getLevelBoundsLength",
    "outputs": [
      {
        "internalType": "uint256",
        "name": "",
        "type": "uint256"
      }
    ],
    "stateMutability": "view",
    "type": "function"
  },
  {
    "inputs": [
      {
        "internalType": "address",
        "name": "",
        "type": "address"
      },
      {
        "internalType": "uint256",
        "name": "",
        "type": "uint256"
      }
    ],
    "name": "latestBuy",
    "outputs": [
      {
        "internalType": "uint256",
        "name": "",
        "type": "uint256"
      }
    ],
    "stateMutability": "view",
    "type": "function"
  },
  {
    "inputs": [],
    "name": "maxTry",
    "outputs": [
      {
        "internalType": "uint256",
        "name": "",
        "type": "uint256"
      }
    ],
    "stateMutability": "view",
    "type": "function"
  },
  {
    "inputs": [],
    "name": "nftAdmin",
    "outputs": [
      {
        "internalType": "address",
        "name": "",
        "type": "address"
      }
    ],
    "stateMutability": "view",
    "type": "function"
  },
  {
    "inputs": [],
    "name": "nftContract",
    "outputs": [
      {
        "internalType": "address",
        "name": "",
        "type": "address"
      }
    ],
    "stateMutability": "view",
    "type": "function"
  },
  {
    "inputs": [
      {
        "internalType": "uint256",
        "name": "",
        "type": "uint256"
      }
    ],
    "name": "nftTokenIds",
    "outputs": [
      {
        "internalType": "uint256",
        "name": "_value",
        "type": "uint256"
      }
    ],
    "stateMutability": "view",
    "type": "function"
  },
  {
    "inputs": [],
    "name": "owner",
    "outputs": [
      {
        "internalType": "address",
        "name": "",
        "type": "address"
      }
    ],
    "stateMutability": "view",
    "type": "function"
  },
  {
    "inputs": [],
    "name": "randNonce",
    "outputs": [
      {
        "internalType": "uint256",
        "name": "",
        "type": "uint256"
      }
    ],
    "stateMutability": "view",
    "type": "function"
  },
  {
    "inputs": [],
    "name": "randOracle",
    "outputs": [
      {
        "internalType": "contract RandOracle",
        "name": "",
        "type": "address"
      }
    ],
    "stateMutability": "view",
    "type": "function"
  },
  {
    "inputs": [],
    "name": "renounceOwnership",
    "outputs": [],
    "stateMutability": "nonpayable",
    "type": "function"
  },
  {
    "inputs": [
      {
        "internalType": "address",
        "name": "_baseToken",
        "type": "address"
      },
      {
        "internalType": "uint256",
        "name": "_basePrice",
        "type": "uint256"
      }
    ],
    "name": "setBaseTradingPair",
    "outputs": [],
    "stateMutability": "nonpayable",
    "type": "function"
  },
  {
    "inputs": [
      {
        "internalType": "uint256",
        "name": "_maxTry",
        "type": "uint256"
      }
    ],
    "name": "setMaxTry",
    "outputs": [],
    "stateMutability": "nonpayable",
    "type": "function"
  },
  {
    "inputs": [
      {
        "internalType": "address",
        "name": "tokenSrc",
        "type": "address"
      },
      {
        "internalType": "address",
        "name": "buyer",
        "type": "address"
      },
      {
        "internalType": "uint256",
        "name": "numberToBuy",
        "type": "uint256"
      },
      {
        "internalType": "uint256",
        "name": "price",
        "type": "uint256"
      }
    ],
    "name": "tradeToken",
    "outputs": [],
    "stateMutability": "payable",
    "type": "function"
  },
  {
    "inputs": [
      {
        "internalType": "address",
        "name": "newOwner",
        "type": "address"
      }
    ],
    "name": "transferOwnership",
    "outputs": [],
    "stateMutability": "nonpayable",
    "type": "function"
  },
  {
    "stateMutability": "payable",
    "type": "receive"
  }
]
